aiovcenter/__init__.py
aiovcenter/vcs_client.py
aiovcenter-0.1.0.post3.dist-info/METADATA
aiovcenter-0.1.0.post3.dist-info/WHEEL
aiovcenter-0.1.0.post3.dist-info/top_level.txt
aiovcenter-0.1.0.post3.dist-info/RECORD
